dddg/__init__.py
dddg/__main__.py
dddg/config/__init__.py
dddg/config/default.toml
dddg/duck.py
dddg/image.py
dddg/inference/__init__.py
dddg/inference/infer.py
dddg/inference/labels.toml
dddg/inference/model.pt
dddg/inference/model.py
dddg/loader.py
dddg/solver.py
dddg-0.1.2.dist-info/entry_points.txt
dddg-0.1.2.dist-info/LICENSE
dddg-0.1.2.dist-info/WHEEL
dddg-0.1.2.dist-info/METADATA
dddg-0.1.2.dist-info/RECORD
