Metadata-Version: 2.1
Name: dddg
Version: 0.1.2
Summary: dddg game solver
Author: ionite34
Author-email: dev@ionite.io
Requires-Python: >=3.7,<3.11
Classifier: Programming Language :: Python :: 3
Classifier: Programming Language :: Python :: 3.7
Classifier: Programming Language :: Python :: 3.8
Classifier: Programming Language :: Python :: 3.9
Classifier: Programming Language :: Python :: 3.10
Requires-Dist: click (>=8.1.3,<9.0.0)
Requires-Dist: opencv-python (==4.5.5.62)
Requires-Dist: requests (>=2.28.1,<3.0.0)
Requires-Dist: torch (>=1.12.1,<2.0.0)
Requires-Dist: torchvision (>=0.13.1,<0.14.0)
Requires-Dist: webcolors (>=1.12,<2.0)
